pingtile/__init__.py
pingtile/ex_imglbl2tile.py
pingtile/imglbl2tile.py
pingtile/mosaic2tile.py
pingtile/rf_upload.py
pingtile/sonogramMovWin.py
pingtile/utils.py
pingtile/utils_TestShadowModel.py
pingtile/version.py
pingtile-0.0.1b14.dist-info/METADATA
pingtile-0.0.1b14.dist-info/WHEEL
pingtile-0.0.1b14.dist-info/top_level.txt
pingtile-0.0.1b14.dist-info/RECORD
